sam_audio_infer/__init__.py
sam_audio_infer/chunking.py
sam_audio_infer/cli.py
sam_audio_infer/download.py
sam_audio_infer/inference.py
sam_audio_infer/lite.py
sam_audio_infer/memory.py
sam_audio_infer/model.py
sam_audio_infer/precision.py
sam_audio_infer/py.typed
sam_audio_infer/types.py
sam_audio_infer-0.1.1.dist-info/METADATA
sam_audio_infer-0.1.1.dist-info/WHEEL
sam_audio_infer-0.1.1.dist-info/entry_points.txt
sam_audio_infer-0.1.1.dist-info/RECORD
