Metadata-Version: 2.4
Name: sam-audio-infer
Version: 0.1.1
Summary: Optimized inference package for Meta's SAM-Audio model with VRAM-efficient lite mode
Project-URL: Homepage, https://github.com/openmirlab/sam-audio-infer
Project-URL: Documentation, https://github.com/openmirlab/sam-audio-infer#readme
Project-URL: Repository, https://github.com/openmirlab/sam-audio-infer.git
Project-URL: Issues, https://github.com/openmirlab/sam-audio-infer/issues
Author: OpenMIRLab
License-Expression: MIT
Keywords: audio,deep-learning,inference,pytorch,sam-audio,separation
Classifier: Development Status :: 4 - Beta
Classifier: Intended Audience :: Developers
Classifier: Intended Audience :: Science/Research
Classifier: License :: OSI Approved :: MIT License
Classifier: Programming Language :: Python :: 3
Classifier: Programming Language :: Python :: 3.11
Classifier: Programming Language :: Python :: 3.12
Classifier: Topic :: Multimedia :: Sound/Audio
Classifier: Topic :: Scientific/Engineering :: Artificial Intelligence
Requires-Python: >=3.11
Requires-Dist: huggingface-hub>=0.20.0
Requires-Dist: numpy>=1.24.0
Requires-Dist: python-dotenv>=1.0.0
Requires-Dist: torch>=2.0.0
Requires-Dist: torchaudio>=2.0.0
Provides-Extra: dev
Requires-Dist: black>=23.0.0; extra == 'dev'
Requires-Dist: mypy>=1.0.0; extra == 'dev'
Requires-Dist: pytest-cov>=4.0.0; extra == 'dev'
Requires-Dist: pytest>=7.0.0; extra == 'dev'
Requires-Dist: ruff>=0.1.0; extra == 'dev'
